{"py/object": "rasa.core.featurizers.tracker_featurizers.IntentMaxHistoryTrackerFeaturizer", "state_featurizer": {"py/object": "rasa.core.featurizers.single_state_featurizer.IntentTokenizerSingleStateFeaturizer", "_default_feature_states": {"intent": {"add_contact": 0, "add_reminder": 1, "affirm": 2, "ask_about_functionalities": 3, "ask_functions": 4, "ask_recipe": 5, "back": 6, "call_someone": 7, "cancel_reminder": 8, "check_event_data_form": 9, "confirm_weather": 10, "deny": 11, "find_events": 12, "goodbye": 13, "greet": 14, "light_consume": 15, "light_switch": 16, "new_user": 17, "nlu_fallback": 18, "out_of_scope": 19, "query_food_nutrition_data": 20, "query_walk_recommendation": 21, "query_weather": 22, "restart": 23, "session_start": 24}, "action_name": {"action_listen": 0, "action_restart": 1, "action_session_start": 2, "action_default_fallback": 3, "action_deactivate_loop": 4, "action_revert_fallback_events": 5, "action_default_ask_affirmation": 6, "action_default_ask_rephrase": 7, "action_two_stage_fallback": 8, "action_unlikely_intent": 9, "action_back": 10, "...": 11, "action_extract_slots": 12, "action_greet_user": 13, "action_ask_recipe": 14, "action_switch_lights": 15, "utter_greet": 16, "action_create_contact": 17, "action_check_light_consume": 18, "action_confirm_weather": 19, "action_create_event": 20, "action_check_event": 21, "validate_check_event_data_form": 22, "action_get_weather": 23, "action_call_someone": 24, "action_query_walk": 25, "action_query_food_nutrition_data": 26, "action_about_functionalities": 27, "utter_anyelse": 28, "utter_cancel": 29, "utter_default": 30, "utter_dispose": 31, "utter_done": 32, "utter_goodbye": 33, "utter_info": 34, "check_event_data_form": 35}, "entities": {"day": 0, "day_of_week": 1, "duration": 2, "event": 3, "hour": 4, "location": 5, "logged_in": 6, "month": 7, "name": 8, "number": 9, "occurrence": 10, "person": 11, "place": 12, "recipe": 13, "switch": 14, "weather": 15}, "slots": {"event_0": 0, "hour_0": 1, "day_of_week_0": 2, "day_0": 3, "month_0": 4, "person_0": 5, "location_0": 6, "duration_0": 7, "occurrence_0": 8, "weather_0": 9, "recipe_0": 10, "switch_0": 11, "number_0": 12, "place_0": 13, "name_0": 14, "logged_in_0": 15}, "active_loop": {"check_event_data_form": 0}}, "action_texts": [], "entity_tag_specs": []}, "max_history": 5, "remove_duplicates": true}